jupyterlab_image_editor/__init__.py
jupyterlab_image_editor/_version.py
jupyterlab_image_editor/labextension/package.json
jupyterlab_image_editor/labextension/static/618.af16bcd5771d56b6fd00.js
jupyterlab_image_editor/labextension/static/618.af16bcd5771d56b6fd00.js.LICENSE.txt
jupyterlab_image_editor/labextension/static/659.1710ec754124a2df677a.js
jupyterlab_image_editor/labextension/static/659.1710ec754124a2df677a.js.LICENSE.txt
jupyterlab_image_editor/labextension/static/747.2cf5b6147d5dd1bf2672.js
jupyterlab_image_editor/labextension/static/783.875f172928e1758d63a8.js
jupyterlab_image_editor/labextension/static/837.7709ec3824e0c1256322.js
jupyterlab_image_editor/labextension/static/94.dd3e169d2639507de407.js
jupyterlab_image_editor/labextension/static/remoteEntry.efc530d73892d3d1a998.js
jupyterlab_image_editor/labextension/static/style.js
jupyterlab_image_editor/labextension/static/third-party-licenses.json
jupyterlab_image_editor-0.1.0.data/data/share/jupyter/labextensions/image-editor/install.json
jupyterlab_image_editor-0.1.0.data/data/share/jupyter/labextensions/image-editor/package.json
jupyterlab_image_editor-0.1.0.data/data/share/jupyter/labextensions/image-editor/static/618.af16bcd5771d56b6fd00.js
jupyterlab_image_editor-0.1.0.data/data/share/jupyter/labextensions/image-editor/static/618.af16bcd5771d56b6fd00.js.LICENSE.txt
jupyterlab_image_editor-0.1.0.data/data/share/jupyter/labextensions/image-editor/static/659.1710ec754124a2df677a.js
jupyterlab_image_editor-0.1.0.data/data/share/jupyter/labextensions/image-editor/static/659.1710ec754124a2df677a.js.LICENSE.txt
jupyterlab_image_editor-0.1.0.data/data/share/jupyter/labextensions/image-editor/static/747.2cf5b6147d5dd1bf2672.js
jupyterlab_image_editor-0.1.0.data/data/share/jupyter/labextensions/image-editor/static/783.875f172928e1758d63a8.js
jupyterlab_image_editor-0.1.0.data/data/share/jupyter/labextensions/image-editor/static/837.7709ec3824e0c1256322.js
jupyterlab_image_editor-0.1.0.dist-info/LICENSE
jupyterlab_image_editor-0.1.0.dist-info/METADATA
jupyterlab_image_editor-0.1.0.dist-info/WHEEL
jupyterlab_image_editor-0.1.0.dist-info/top_level.txt
jupyterlab_image_editor-0.1.0.dist-info/RECORD
